{
  "type": "File",
  "start": 0,
  "end": 143,
  "loc": {
    "start": {
      "line": 1,
      "column": 0
    },
    "end": {
      "line": 4,
      "column": 44
    }
  },
  "program": {
    "type": "Program",
    "start": 0,
    "end": 143,
    "loc": {
      "start": {
        "line": 1,
        "column": 0
      },
      "end": {
        "line": 4,
        "column": 44
      }
    },
    "sourceType": "module",
    "body": [
      {
        "type": "ImportDeclaration",
        "start": 0,
        "end": 36,
        "loc": {
          "start": {
            "line": 1,
            "column": 0
          },
          "end": {
            "line": 1,
            "column": 36
          }
        },
        "specifiers": [
          {
            "type": "ImportSpecifier",
            "start": 9,
            "end": 20,
            "loc": {
              "start": {
                "line": 1,
                "column": 9
              },
              "end": {
                "line": 1,
                "column": 20
              }
            },
            "imported": {
              "type": "Identifier",
              "start": 9,
              "end": 20,
              "loc": {
                "start": {
                  "line": 1,
                  "column": 9
                },
                "end": {
                  "line": 1,
                  "column": 20
                },
                "identifierName": "createStore"
              },
              "name": "createStore"
            },
            "local": {
              "type": "Identifier",
              "start": 9,
              "end": 20,
              "loc": {
                "start": {
                  "line": 1,
                  "column": 9
                },
                "end": {
                  "line": 1,
                  "column": 20
                },
                "identifierName": "createStore"
              },
              "name": "createStore"
            }
          }
        ],
        "source": {
          "type": "StringLiteral",
          "start": 28,
          "end": 35,
          "loc": {
            "start": {
              "line": 1,
              "column": 28
            },
            "end": {
              "line": 1,
              "column": 35
            }
          },
          "extra": {
            "rawValue": "redux",
            "raw": "\"redux\""
          },
          "value": "redux"
        }
      },
      {
        "type": "ImportDeclaration",
        "start": 38,
        "end": 95,
        "loc": {
          "start": {
            "line": 2,
            "column": 0
          },
          "end": {
            "line": 2,
            "column": 57
          }
        },
        "specifiers": [
          {
            "type": "ImportDefaultSpecifier",
            "start": 45,
            "end": 60,
            "loc": {
              "start": {
                "line": 2,
                "column": 7
              },
              "end": {
                "line": 2,
                "column": 22
              }
            },
            "local": {
              "type": "Identifier",
              "start": 45,
              "end": 60,
              "loc": {
                "start": {
                  "line": 2,
                  "column": 7
                },
                "end": {
                  "line": 2,
                  "column": 22
                },
                "identifierName": "favoriteReducer"
              },
              "name": "favoriteReducer"
            }
          }
        ],
        "source": {
          "type": "StringLiteral",
          "start": 66,
          "end": 94,
          "loc": {
            "start": {
              "line": 2,
              "column": 28
            },
            "end": {
              "line": 2,
              "column": 56
            }
          },
          "extra": {
            "rawValue": "./Reducers/favoriteReducer",
            "raw": "\"./Reducers/favoriteReducer\""
          },
          "value": "./Reducers/favoriteReducer"
        }
      },
      {
        "type": "ExportDefaultDeclaration",
        "start": 99,
        "end": 143,
        "loc": {
          "start": {
            "line": 4,
            "column": 0
          },
          "end": {
            "line": 4,
            "column": 44
          }
        },
        "declaration": {
          "type": "CallExpression",
          "start": 114,
          "end": 142,
          "loc": {
            "start": {
              "line": 4,
              "column": 15
            },
            "end": {
              "line": 4,
              "column": 43
            }
          },
          "callee": {
            "type": "Identifier",
            "start": 114,
            "end": 125,
            "loc": {
              "start": {
                "line": 4,
                "column": 15
              },
              "end": {
                "line": 4,
                "column": 26
              },
              "identifierName": "createStore"
            },
            "name": "createStore"
          },
          "arguments": [
            {
              "type": "Identifier",
              "start": 126,
              "end": 141,
              "loc": {
                "start": {
                  "line": 4,
                  "column": 27
                },
                "end": {
                  "line": 4,
                  "column": 42
                },
                "identifierName": "favoriteReducer"
              },
              "name": "favoriteReducer"
            }
          ],
          "leadingComments": [],
          "trailingComments": []
        }
      }
    ],
    "directives": []
  },
  "comments": [],
  "tokens": [
    {
      "type": {
        "label": "import",
        "keyword": "import",
        "beforeExpr": false,
        "startsExpr": true,
        "rightAssociative": false,
        "isLoop": false,
        "isAssign": false,
        "prefix": false,
        "postfix": false,
        "binop": null,
        "updateContext": null
      },
      "value": "import",
      "start": 0,
      "end": 6,
      "loc": {
        "start": {
          "line": 1,
          "column": 0
        },
        "end": {
          "line": 1,
          "column": 6
        }
      }
    },
    {
      "type": {
        "label": "{",
        "beforeExpr": true,
        "startsExpr": true,
        "rightAssociative": false,
        "isLoop": false,
        "isAssign": false,
        "prefix": false,
        "postfix": false,
        "binop": null
      },
      "start": 7,
      "end": 8,
      "loc": {
        "start": {
          "line": 1,
          "column": 7
        },
        "end": {
          "line": 1,
          "column": 8
        }
      }
    },
    {
      "type": {
        "label": "name",
        "beforeExpr": false,
        "startsExpr": true,
        "rightAssociative": false,
        "isLoop": false,
        "isAssign": false,
        "prefix": false,
        "postfix": false,
        "binop": null
      },
      "value": "createStore",
      "start": 9,
      "end": 20,
      "loc": {
        "start": {
          "line": 1,
          "column": 9
        },
        "end": {
          "line": 1,
          "column": 20
        }
      }
    },
    {
      "type": {
        "label": "}",
        "beforeExpr": false,
        "startsExpr": false,
        "rightAssociative": false,
        "isLoop": false,
        "isAssign": false,
        "prefix": false,
        "postfix": false,
        "binop": null
      },
      "start": 21,
      "end": 22,
      "loc": {
        "start": {
          "line": 1,
          "column": 21
        },
        "end": {
          "line": 1,
          "column": 22
        }
      }
    },
    {
      "type": {
        "label": "name",
        "beforeExpr": false,
        "startsExpr": true,
        "rightAssociative": false,
        "isLoop": false,
        "isAssign": false,
        "prefix": false,
        "postfix": false,
        "binop": null
      },
      "value": "from",
      "start": 23,
      "end": 27,
      "loc": {
        "start": {
          "line": 1,
          "column": 23
        },
        "end": {
          "line": 1,
          "column": 27
        }
      }
    },
    {
      "type": {
        "label": "string",
        "beforeExpr": false,
        "startsExpr": true,
        "rightAssociative": false,
        "isLoop": false,
        "isAssign": false,
        "prefix": false,
        "postfix": false,
        "binop": null,
        "updateContext": null
      },
      "value": "redux",
      "start": 28,
      "end": 35,
      "loc": {
        "start": {
          "line": 1,
          "column": 28
        },
        "end": {
          "line": 1,
          "column": 35
        }
      }
    },
    {
      "type": {
        "label": ";",
        "beforeExpr": true,
        "startsExpr": false,
        "rightAssociative": false,
        "isLoop": false,
        "isAssign": false,
        "prefix": false,
        "postfix": false,
        "binop": null,
        "updateContext": null
      },
      "start": 35,
      "end": 36,
      "loc": {
        "start": {
          "line": 1,
          "column": 35
        },
        "end": {
          "line": 1,
          "column": 36
        }
      }
    },
    {
      "type": {
        "label": "import",
        "keyword": "import",
        "beforeExpr": false,
        "startsExpr": true,
        "rightAssociative": false,
        "isLoop": false,
        "isAssign": false,
        "prefix": false,
        "postfix": false,
        "binop": null,
        "updateContext": null
      },
      "value": "import",
      "start": 38,
      "end": 44,
      "loc": {
        "start": {
          "line": 2,
          "column": 0
        },
        "end": {
          "line": 2,
          "column": 6
        }
      }
    },
    {
      "type": {
        "label": "name",
        "beforeExpr": false,
        "startsExpr": true,
        "rightAssociative": false,
        "isLoop": false,
        "isAssign": false,
        "prefix": false,
        "postfix": false,
        "binop": null
      },
      "value": "favoriteReducer",
      "start": 45,
      "end": 60,
      "loc": {
        "start": {
          "line": 2,
          "column": 7
        },
        "end": {
          "line": 2,
          "column": 22
        }
      }
    },
    {
      "type": {
        "label": "name",
        "beforeExpr": false,
        "startsExpr": true,
        "rightAssociative": false,
        "isLoop": false,
        "isAssign": false,
        "prefix": false,
        "postfix": false,
        "binop": null
      },
      "value": "from",
      "start": 61,
      "end": 65,
      "loc": {
        "start": {
          "line": 2,
          "column": 23
        },
        "end": {
          "line": 2,
          "column": 27
        }
      }
    },
    {
      "type": {
        "label": "string",
        "beforeExpr": false,
        "startsExpr": true,
        "rightAssociative": false,
        "isLoop": false,
        "isAssign": false,
        "prefix": false,
        "postfix": false,
        "binop": null,
        "updateContext": null
      },
      "value": "./Reducers/favoriteReducer",
      "start": 66,
      "end": 94,
      "loc": {
        "start": {
          "line": 2,
          "column": 28
        },
        "end": {
          "line": 2,
          "column": 56
        }
      }
    },
    {
      "type": {
        "label": ";",
        "beforeExpr": true,
        "startsExpr": false,
        "rightAssociative": false,
        "isLoop": false,
        "isAssign": false,
        "prefix": false,
        "postfix": false,
        "binop": null,
        "updateContext": null
      },
      "start": 94,
      "end": 95,
      "loc": {
        "start": {
          "line": 2,
          "column": 56
        },
        "end": {
          "line": 2,
          "column": 57
        }
      }
    },
    {
      "type": {
        "label": "export",
        "keyword": "export",
        "beforeExpr": false,
        "startsExpr": false,
        "rightAssociative": false,
        "isLoop": false,
        "isAssign": false,
        "prefix": false,
        "postfix": false,
        "binop": null,
        "updateContext": null
      },
      "value": "export",
      "start": 99,
      "end": 105,
      "loc": {
        "start": {
          "line": 4,
          "column": 0
        },
        "end": {
          "line": 4,
          "column": 6
        }
      }
    },
    {
      "type": {
        "label": "default",
        "keyword": "default",
        "beforeExpr": true,
        "startsExpr": false,
        "rightAssociative": false,
        "isLoop": false,
        "isAssign": false,
        "prefix": false,
        "postfix": false,
        "binop": null,
        "updateContext": null
      },
      "value": "default",
      "start": 106,
      "end": 113,
      "loc": {
        "start": {
          "line": 4,
          "column": 7
        },
        "end": {
          "line": 4,
          "column": 14
        }
      }
    },
    {
      "type": {
        "label": "name",
        "beforeExpr": false,
        "startsExpr": true,
        "rightAssociative": false,
        "isLoop": false,
        "isAssign": false,
        "prefix": false,
        "postfix": false,
        "binop": null
      },
      "value": "createStore",
      "start": 114,
      "end": 125,
      "loc": {
        "start": {
          "line": 4,
          "column": 15
        },
        "end": {
          "line": 4,
          "column": 26
        }
      }
    },
    {
      "type": {
        "label": "(",
        "beforeExpr": true,
        "startsExpr": true,
        "rightAssociative": false,
        "isLoop": false,
        "isAssign": false,
        "prefix": false,
        "postfix": false,
        "binop": null
      },
      "start": 125,
      "end": 126,
      "loc": {
        "start": {
          "line": 4,
          "column": 26
        },
        "end": {
          "line": 4,
          "column": 27
        }
      }
    },
    {
      "type": {
        "label": "name",
        "beforeExpr": false,
        "startsExpr": true,
        "rightAssociative": false,
        "isLoop": false,
        "isAssign": false,
        "prefix": false,
        "postfix": false,
        "binop": null
      },
      "value": "favoriteReducer",
      "start": 126,
      "end": 141,
      "loc": {
        "start": {
          "line": 4,
          "column": 27
        },
        "end": {
          "line": 4,
          "column": 42
        }
      }
    },
    {
      "type": {
        "label": ")",
        "beforeExpr": false,
        "startsExpr": false,
        "rightAssociative": false,
        "isLoop": false,
        "isAssign": false,
        "prefix": false,
        "postfix": false,
        "binop": null
      },
      "start": 141,
      "end": 142,
      "loc": {
        "start": {
          "line": 4,
          "column": 42
        },
        "end": {
          "line": 4,
          "column": 43
        }
      }
    },
    {
      "type": {
        "label": ";",
        "beforeExpr": true,
        "startsExpr": false,
        "rightAssociative": false,
        "isLoop": false,
        "isAssign": false,
        "prefix": false,
        "postfix": false,
        "binop": null,
        "updateContext": null
      },
      "start": 142,
      "end": 143,
      "loc": {
        "start": {
          "line": 4,
          "column": 43
        },
        "end": {
          "line": 4,
          "column": 44
        }
      }
    },
    {
      "type": {
        "label": "eof",
        "beforeExpr": false,
        "startsExpr": false,
        "rightAssociative": false,
        "isLoop": false,
        "isAssign": false,
        "prefix": false,
        "postfix": false,
        "binop": null,
        "updateContext": null
      },
      "start": 143,
      "end": 143,
      "loc": {
        "start": {
          "line": 4,
          "column": 44
        },
        "end": {
          "line": 4,
          "column": 44
        }
      }
    }
  ]
}